jwlib/__init__.py
jwlib/common.py
jwlib/pub.py
jwlib/py.typed
jwlib/search.py
jwlib/weblang.py
jwlib/media/__init__.py
jwlib/media/const.py
jwlib/media/endpoints.py
jwlib/media/imagetable.py
jwlib/media/language.py
jwlib/media/session.py
jwlib-1.0.0b2.dist-info/licenses/LICENSE
jwlib-1.0.0b2.dist-info/METADATA
jwlib-1.0.0b2.dist-info/WHEEL
jwlib-1.0.0b2.dist-info/top_level.txt
jwlib-1.0.0b2.dist-info/RECORD
