Metadata-Version: 2.4
Name: jwlib
Version: 1.0.0b2
Summary: Wrapper for jw.org APIs
Author-email: allejok96 <allejok96@gmail.com>
Project-URL: Homepage, https://github.com/allejok96/jwlib
Project-URL: Documentation, https://jwlib.readthedocs.io/en/latest
Project-URL: Issues, https://github.com/allejok96/jwlib/issues
Project-URL: Changelog, https://github.com/allejok96/jwlib/blob/main/HISTORY.rst
Keywords: jw,jworg
Classifier: Development Status :: 3 - Alpha
Classifier: Intended Audience :: Developers
Classifier: License :: OSI Approved :: GNU General Public License v3 (GPLv3)
Classifier: Operating System :: OS Independent
Classifier: Programming Language :: Python :: 3.8
Classifier: Topic :: Internet :: WWW/HTTP :: Indexing/Search
Classifier: Topic :: Religion
Classifier: Topic :: Software Development :: Libraries :: Python Modules
Classifier: Typing :: Typed
Requires-Python: >=3.8
License-File: LICENSE
Provides-Extra: dev
Requires-Dist: coverage; extra == "dev"
Requires-Dist: mypy; extra == "dev"
Requires-Dist: Pillow; extra == "dev"
Requires-Dist: pytest-recording; extra == "dev"
Requires-Dist: tabulate; extra == "dev"
Requires-Dist: pip-tools; extra == "dev"
Provides-Extra: docs
Requires-Dist: Sphinx; extra == "docs"
Requires-Dist: sphinx_rtd_theme; extra == "docs"
Requires-Dist: watchdog; extra == "docs"
Dynamic: license-file
